felt/__init__.py
felt/__version__.py
felt/estimate.py
felt/matrix.py
felt/movement.py
felt/network.py
felt/routing.py
felt-0.1.dist-info/METADATA
felt-0.1.dist-info/WHEEL
felt-0.1.dist-info/top_level.txt
felt-0.1.dist-info/RECORD
